abja_mpl/__init__.py
abja_mpl/subplots.py
abja_mpl-0.0.1.dist-info/licenses/LICENSE
abja_mpl-0.0.1.dist-info/METADATA
abja_mpl-0.0.1.dist-info/WHEEL
abja_mpl-0.0.1.dist-info/top_level.txt
abja_mpl-0.0.1.dist-info/RECORD
