Metadata-Version: 2.4
Name: abja_mpl
Version: 0.0.1
Summary: A customized version of matplotlib
Author-email: Abbas Jazaeri <abja@dhigroup.com>
License: Copyright (c) 2025 DHI Water and Environment Inc
Classifier: Programming Language :: Python :: 3
Classifier: Operating System :: OS Independent
Requires-Python: >=3.9
License-File: LICENSE
Requires-Dist: numpy
Requires-Dist: matplotlib
Requires-Dist: cycler
Dynamic: license-file
